[{"date":"2024-02-28","bill_number":"HB338","bill_title":"Siting of data centers; locality may perform site assessment before approval.","vote_question":"Senate: Continued to 2025 in General Laws and Technology (9-Y 3-N 3-A)","vote_result":"Vote (9-3)","member_vote":"No","session":"2149","roll_call":"1464650","chamber":"Senate","keywords":"Environment; Technology"},{"date":"2024-02-28","bill_number":"HB158","bill_title":"Firearm locking device; required for sale or transfer of firearm.","vote_question":"Senate: Continued to 2025 in Courts of Justice (15-Y 0-N)","vote_result":"Vote (15-0)","member_vote":"Yes","session":"2149","roll_call":"1464807","chamber":"Senate","keywords":"Environment; Criminal Justice"},{"date":"2024-02-28","bill_number":"HB878","bill_title":"Affordable housing; purchase of development rights.","vote_question":"Senate: Continued to 2025 in General Laws and Technology (15-Y 0-N)","vote_result":"Vote (15-0)","member_vote":"Yes","session":"2149","roll_call":"1464934","chamber":"Senate","keywords":"Technology; Housing"},{"date":"2024-02-28","bill_number":"HB1355","bill_title":"Information Technology Access Act; numerous organizational changes to Act.","vote_question":"Senate: Continued to 2025 in General Laws and Technology (15-Y 0-N)","vote_result":"Vote (15-0)","member_vote":"Yes","session":"2149","roll_call":"1465141","chamber":"Senate","keywords":"Defense; Technology"},{"date":"2024-02-28","bill_number":"HB1101","bill_title":"Virginia Public Procurement Act; adds to definition of professional services.","vote_question":"Senate: Reported from General Laws and Technology with amendment (15-Y 0-N)","vote_result":"Vote (15-0)","member_vote":"Yes","session":"2149","roll_call":"1465208","chamber":"Senate","keywords":"Environment; Technology"},{"date":"2024-02-27","bill_number":"HB420","bill_title":"Federal park operations; temporary funding.","vote_question":"Senate: Reported from Agriculture, Conservation and Natural Resources (14-Y 0-N)","vote_result":"Vote (14-0)","member_vote":"Yes","session":"2149","roll_call":"1465163","chamber":"Senate","keywords":"Environment; Agriculture"},{"date":"2024-02-26","bill_number":"HB1054","bill_title":"Vegetative growth on certain property; maintenance.","vote_question":"Senate: Continued to 2025 in Local Government (14-Y 0-N)","vote_result":"Vote (14-0)","member_vote":"Yes","session":"2149","roll_call":"1464830","chamber":"Senate","keywords":"Healthcare; Economy; Social Services"},{"date":"2024-02-26","bill_number":"HB951","bill_title":"Local government; authority, service employees, transition period.","vote_question":"Senate: Reported from Local Government (8-Y 7-N)","vote_result":"Vote (8-7)","member_vote":"Yes","session":"2149","roll_call":"1464955","chamber":"Senate","keywords":"Education; Environment; Infrastructure; Agriculture"},{"date":"2024-02-26","bill_number":"HB725","bill_title":"Local government; powers, conveyance of real property, public hearing requirement.","vote_question":"Senate: Continued to 2025 in Local Government (12-Y 3-N)","vote_result":"Vote (12-3)","member_vote":"Yes","session":"2149","roll_call":"1465145","chamber":"Senate","keywords":"Infrastructure; Housing"},{"date":"2024-02-21","bill_number":"HB141","bill_title":"Veterans' Fellowship for State Government Pilot Program; created, report.","vote_question":"Senate: Reported from General Laws and Technology (8-Y 0-N)","vote_result":"Vote (8-0)","member_vote":"Yes","session":"2149","roll_call":"1464779","chamber":"Senate","keywords":"Education; Economy; Environment; Defense; Technology"},{"date":"2024-02-21","bill_number":"HB1434","bill_title":"Mattaponi Indian Tribe; DOF to convey tracts of land in Sandy Point State Forest to the Tribe.","vote_question":"Senate: Continued to 2025 in Courts of Justice (15-Y 0-N)","vote_result":"Vote (15-0)","member_vote":"Yes","session":"2149","roll_call":"1464819","chamber":"Senate","keywords":"Environment"},{"date":"2024-02-21","bill_number":"HB1273","bill_title":"VA Public Procurement Act; additional public works contract requirements, delayed effective date.","vote_question":"Senate: Reported from General Laws and Technology (9-Y 5-N)","vote_result":"Vote (9-5)","member_vote":"Yes","session":"2149","roll_call":"1464872","chamber":"Senate","keywords":"Technology; Housing"},{"date":"2024-02-20","bill_number":"HB878","bill_title":"Affordable housing; purchase of development rights.","vote_question":"Senate: Constitutional reading dispensed (39-Y 0-N)","vote_result":"Vote (39-0)","member_vote":"Yes","session":"2149","roll_call":"1464933","chamber":"Senate","keywords":"Housing"},{"date":"2024-02-20","bill_number":"HB1403","bill_title":"Dam Safety, Flood Prevention, and Protection Assistance Fund; percentage of funds available.","vote_question":"Senate: Reported from Agriculture, Conservation and Natural Resources with substitute (15-Y 0-N)","vote_result":"Vote (15-0)","member_vote":"Yes","session":"2149","roll_call":"1465154","chamber":"Senate","keywords":"Environment; Agriculture"},{"date":"2024-02-19","bill_number":"HB1070","bill_title":"Southwest Regional Recreation Authority; powers.","vote_question":"Senate: Reported from Local Government with substitute (14-Y 0-N)","vote_result":"Vote (14-0)","member_vote":"Yes","session":"2149","roll_call":"1464741","chamber":"Senate","keywords":"Environment; Infrastructure"},{"date":"2024-02-19","bill_number":"HB1263","bill_title":"Abolition of juvenile fines and fees; criminal offenses.","vote_question":"Senate: Reported from Courts of Justice with substitute (8-Y 5-N)","vote_result":"Vote (8-5)","member_vote":"Yes","session":"2149","roll_call":"1464915","chamber":"Senate","keywords":"Criminal Justice; Housing"},{"date":"2024-02-19","bill_number":"HB697","bill_title":"Synthetic media; use in furtherance of crimes involving fraud, etc., report.","vote_question":"Senate: Continued to 2025 in Courts of Justice (11-Y 2-N)","vote_result":"Vote (11-2)","member_vote":"No","session":"2149","roll_call":"1464921","chamber":"Senate","keywords":"Economy; Environment; Criminal Justice; Housing"},{"date":"2024-02-19","bill_number":"HB878","bill_title":"Affordable housing; purchase of development rights.","vote_question":"Senate: Reported from Local Government with amendments (9-Y 6-N)","vote_result":"Vote (9-6)","member_vote":"Yes","session":"2149","roll_call":"1464932","chamber":"Senate","keywords":"Housing"},{"date":"2024-02-14","bill_number":"HB527","bill_title":"Charitable Sports Raffle Act; established, penalties.","vote_question":"Senate: Reported from General Laws and Technology with substitute (15-Y 0-N)","vote_result":"Vote (15-0)","member_vote":"Yes","session":"2149","roll_call":"1464797","chamber":"Senate","keywords":"Environment; Criminal Justice; Technology; Agriculture"},{"date":"2024-02-14","bill_number":"HB774","bill_title":"Alcohol safety action program; local administrative fee.","vote_question":"Senate: Continued to 2025 in Courts of Justice (8-Y 7-N)","vote_result":"Vote (8-7)","member_vote":"Yes","session":"2149","roll_call":"1464845","chamber":"Senate","keywords":""},{"date":"2024-02-13","bill_number":"SB302","bill_title":"Virginia First Manufacturing Incentive Program; Manufacturing Development Commission to create.","vote_question":"Senate: Constitutional reading dispensed (39-Y 0-N)","vote_result":"Vote (39-0)","member_vote":"Yes","session":"2149","roll_call":"1464994","chamber":"Senate","keywords":"Economy; Infrastructure; Technology"},{"date":"2024-02-13","bill_number":"SB302","bill_title":"Virginia First Manufacturing Incentive Program; Manufacturing Development Commission to create.","vote_question":"Senate: Passed Senate (40-Y 0-N)","vote_result":"Passed (40-0)","member_vote":"Yes","session":"2149","roll_call":"1464995","chamber":"Senate","keywords":"Economy; Infrastructure; Technology"},{"date":"2024-02-13","bill_number":"SB427","bill_title":"Petition for modification of a sentence; eligibility, procedures.","vote_question":"Senate: Constitutional reading dispensed (40-Y 0-N)","vote_result":"Vote (40-0)","member_vote":"Yes","session":"2149","roll_call":"1465010","chamber":"Senate","keywords":"Criminal Justice; Housing"},{"date":"2024-02-13","bill_number":"SB427","bill_title":"Petition for modification of a sentence; eligibility, procedures.","vote_question":"Senate: Passed Senate (21-Y 19-N)","vote_result":"Passed (21-19)","member_vote":"Yes","session":"2149","roll_call":"1465011","chamber":"Senate","keywords":"Criminal Justice; Housing"},{"date":"2024-02-13","bill_number":"SB347","bill_title":"VA Military Survivors & Dependents Education Program; work group to evaluate, etc., Program.","vote_question":"Senate: Constitutional reading dispensed (39-Y 0-N)","vote_result":"Vote (39-0)","member_vote":"Yes","session":"2149","roll_call":"1465116","chamber":"Senate","keywords":"Healthcare; Education; Economy; Defense"},{"date":"2024-02-13","bill_number":"SB347","bill_title":"VA Military Survivors & Dependents Education Program; work group to evaluate, etc., Program.","vote_question":"Senate: Passed Senate (40-Y 0-N)","vote_result":"Passed (40-0)","member_vote":"Yes","session":"2149","roll_call":"1465117","chamber":"Senate","keywords":"Healthcare; Education; Economy; Defense"},{"date":"2024-02-12","bill_number":"SB270","bill_title":"Presidential primaries; ranked choice voting, effective clause.","vote_question":"Senate: Read third time and passed Senate (21-Y 19-N)","vote_result":"Passed (21-19)","member_vote":"Yes","session":"2149","roll_call":"1464668","chamber":"Senate","keywords":"Elections"},{"date":"2024-02-12","bill_number":"SB359","bill_title":"Consumer Data Protection Act; social media platforms, addictive feed.","vote_question":"Senate: Read third time and passed Senate (40-Y 0-N)","vote_result":"Passed (40-0)","member_vote":"Yes","session":"2149","roll_call":"1464716","chamber":"Senate","keywords":"Technology; Housing"},{"date":"2024-02-12","bill_number":"SB594","bill_title":"Emergency medical personnel; EMS Advisory Board to examine requirements to join program.","vote_question":"Senate: Constitutional reading dispensed (40-Y 0-N)","vote_result":"Vote (40-0)","member_vote":"Yes","session":"2149","roll_call":"1464722","chamber":"Senate","keywords":"Healthcare; Education; Environment; Social Services"},{"date":"2024-02-12","bill_number":"SB594","bill_title":"Emergency medical personnel; EMS Advisory Board to examine requirements to join program.","vote_question":"Senate: Passed Senate (40-Y 0-N)","vote_result":"Passed (40-0)","member_vote":"Yes","session":"2149","roll_call":"1464723","chamber":"Senate","keywords":"Healthcare; Education; Environment; Social Services"},{"date":"2024-02-12","bill_number":"SB697","bill_title":"Solar and energy facilities; local regulation.","vote_question":"Senate: Read third time and passed Senate (21-Y 18-N)","vote_result":"Passed (21-18)","member_vote":"Yes","session":"2149","roll_call":"1464775","chamber":"Senate","keywords":"Environment"},{"date":"2024-02-12","bill_number":"SB563","bill_title":"Regional career and technical education program; establishing in Planning District 2.","vote_question":"Senate: Constitutional reading dispensed (40-Y 0-N)","vote_result":"Vote (40-0)","member_vote":"Yes","session":"2149","roll_call":"1464834","chamber":"Senate","keywords":"Education; Economy; Environment"},{"date":"2024-02-12","bill_number":"SB563","bill_title":"Regional career and technical education program; establishing in Planning District 2.","vote_question":"Senate: Passed Senate (40-Y 0-N)","vote_result":"Passed (40-0)","member_vote":"Yes","session":"2149","roll_call":"1464835","chamber":"Senate","keywords":"Education; Economy; Environment"},{"date":"2024-02-12","bill_number":"SB315","bill_title":"Voter registration; registration of DMV customers, updates to existing registration.","vote_question":"Senate: Read third time and passed Senate (21-Y 19-N)","vote_result":"Passed (21-19)","member_vote":"Yes","session":"2149","roll_call":"1464904","chamber":"Senate","keywords":"Economy; Environment; Housing; Elections"},{"date":"2024-02-12","bill_number":"SB571","bill_title":"Synthetic media; expands applicability of provisions related to defamation, etc., penalty.","vote_question":"Senate: Continued to 2025 in Courts of Justice (14-Y 0-N)","vote_result":"Vote (14-0)","member_vote":"Yes","session":"2149","roll_call":"1464967","chamber":"Senate","keywords":"Economy; Criminal Justice; Housing"},{"date":"2024-02-12","bill_number":"SB302","bill_title":"Virginia First Manufacturing Incentive Program; Manufacturing Development Commission to create.","vote_question":"Senate: Constitutional reading dispensed (40-Y 0-N)","vote_result":"Vote (40-0)","member_vote":"Yes","session":"2149","roll_call":"1464993","chamber":"Senate","keywords":"Economy; Infrastructure; Technology"},{"date":"2024-02-12","bill_number":"SJR19","bill_title":"Roadway & pedestrian improvements in Gainesville; VDOT to study implementation in Prince Wm. County.","vote_question":"Senate: Reading waived (39-Y 0-N)","vote_result":"Vote (39-0)","member_vote":"Yes","session":"2149","roll_call":"1465015","chamber":"Senate","keywords":"Environment; Infrastructure"},{"date":"2024-02-12","bill_number":"SB590","bill_title":"Community services boards; emergency services and core of services.","vote_question":"Senate: Constitutional reading dispensed (40-Y 0-N)","vote_result":"Vote (40-0)","member_vote":"Yes","session":"2149","roll_call":"1465028","chamber":"Senate","keywords":"Healthcare; Defense"},{"date":"2024-02-12","bill_number":"SB590","bill_title":"Community services boards; emergency services and core of services.","vote_question":"Senate: Passed Senate (40-Y 0-N)","vote_result":"Passed (40-0)","member_vote":"Yes","session":"2149","roll_call":"1465029","chamber":"Senate","keywords":"Healthcare; Defense"},{"date":"2024-02-12","bill_number":"SB347","bill_title":"VA Military Survivors & Dependents Education Program; work group to evaluate, etc., Program.","vote_question":"Senate: Constitutional reading dispensed (40-Y 0-N)","vote_result":"Vote (40-0)","member_vote":"Yes","session":"2149","roll_call":"1465115","chamber":"Senate","keywords":"Healthcare; Education; Economy; Defense"},{"date":"2024-02-09","bill_number":"SB575","bill_title":"Discharge plans; copies to public elementary and secondary schools.","vote_question":"Senate: Constitutional reading dispensed (40-Y 0-N)","vote_result":"Vote (40-0)","member_vote":"Yes","session":"2149","roll_call":"1464663","chamber":"Senate","keywords":"Healthcare; Education; Criminal Justice; Housing"},{"date":"2024-02-09","bill_number":"SB575","bill_title":"Discharge plans; copies to public elementary and secondary schools.","vote_question":"Senate: Passed Senate (40-Y 0-N)","vote_result":"Passed (40-0)","member_vote":"Yes","session":"2149","roll_call":"1464664","chamber":"Senate","keywords":"Healthcare; Education; Criminal Justice; Housing"},{"date":"2024-02-09","bill_number":"SB636","bill_title":"Transcranial magnetic stimulation; DBHDS to establish pilot program for veterans.","vote_question":"Senate: Constitutional reading dispensed (40-Y 0-N)","vote_result":"Vote (40-0)","member_vote":"Yes","session":"2149","roll_call":"1464706","chamber":"Senate","keywords":"Environment; Defense"},{"date":"2024-02-09","bill_number":"SB636","bill_title":"Transcranial magnetic stimulation; DBHDS to establish pilot program for veterans.","vote_question":"Senate: Passed Senate (40-Y 0-N)","vote_result":"Passed (40-0)","member_vote":"Yes","session":"2149","roll_call":"1464707","chamber":"Senate","keywords":"Environment; Defense"},{"date":"2024-02-09","bill_number":"SB594","bill_title":"Emergency medical personnel; EMS Advisory Board to examine requirements to join program.","vote_question":"Senate: Constitutional reading dispensed (39-Y 0-N)","vote_result":"Vote (39-0)","member_vote":"Yes","session":"2149","roll_call":"1464721","chamber":"Senate","keywords":"Healthcare; Education; Environment; Social Services"},{"date":"2024-02-09","bill_number":"SB280","bill_title":"Health care; decision-making, definitions, medical aid in dying, penalties.","vote_question":"Senate: Read third time and passed Senate (21-Y 19-N)","vote_result":"Passed (21-19)","member_vote":"Yes","session":"2149","roll_call":"1464731","chamber":"Senate","keywords":"Healthcare; Criminal Justice"},{"date":"2024-02-09","bill_number":"SB563","bill_title":"Regional career and technical education program; establishing in Planning District 2.","vote_question":"Senate: Constitutional reading dispensed (39-Y 0-N)","vote_result":"Vote (39-0)","member_vote":"Yes","session":"2149","roll_call":"1464833","chamber":"Senate","keywords":"Education; Economy; Environment"},{"date":"2024-02-09","bill_number":"SJR22","bill_title":"Virginia State Police, retired; TAX to study reducing economic stress.","vote_question":"Senate: Reading waived (39-Y 0-N)","vote_result":"Vote (39-0)","member_vote":"Yes","session":"2149","roll_call":"1464836","chamber":"Senate","keywords":"Economy; Environment; Criminal Justice"},{"date":"2024-02-09","bill_number":"SB593","bill_title":"Workers' compensation benefits; post-traumatic stress disorder incurred by firefighters, etc.","vote_question":"Senate: Constitutional reading dispensed (40-Y 0-N)","vote_result":"Vote (40-0)","member_vote":"Yes","session":"2149","roll_call":"1464855","chamber":"Senate","keywords":""},{"date":"2024-02-09","bill_number":"SB593","bill_title":"Workers' compensation benefits; post-traumatic stress disorder incurred by firefighters, etc.","vote_question":"Senate: Passed Senate (40-Y 0-N)","vote_result":"Passed (40-0)","member_vote":"Yes","session":"2149","roll_call":"1464856","chamber":"Senate","keywords":""},{"date":"2024-02-09","bill_number":"SB304","bill_title":"Zoning; development and use of accessory dwelling units.","vote_question":"Senate: Engrossment reconsidered by Senate (40-Y 0-N)","vote_result":"Vote (40-0)","member_vote":"Yes","session":"2149","roll_call":"1464896","chamber":"Senate","keywords":""},{"date":"2024-02-09","bill_number":"SB304","bill_title":"Zoning; development and use of accessory dwelling units.","vote_question":"Senate: Constitutional reading dispensed (38-Y 2-N)","vote_result":"Vote (38-2)","member_vote":"Yes","session":"2149","roll_call":"1464897","chamber":"Senate","keywords":""},{"date":"2024-02-09","bill_number":"SB304","bill_title":"Zoning; development and use of accessory dwelling units.","vote_question":"Senate: Passed Senate (22-Y 18-N)","vote_result":"Passed (22-18)","member_vote":"Yes","session":"2149","roll_call":"1464898","chamber":"Senate","keywords":""},{"date":"2024-02-09","bill_number":"SJR19","bill_title":"Roadway & pedestrian improvements in Gainesville; VDOT to study implementation in Prince Wm. County.","vote_question":"Senate: Reading waived (39-Y 0-N)","vote_result":"Vote (39-0)","member_vote":"Yes","session":"2149","roll_call":"1465014","chamber":"Senate","keywords":"Environment; Infrastructure"},{"date":"2024-02-09","bill_number":"SB590","bill_title":"Community services boards; emergency services and core of services.","vote_question":"Senate: Constitutional reading dispensed (39-Y 0-N)","vote_result":"Vote (39-0)","member_vote":"Yes","session":"2149","roll_call":"1465027","chamber":"Senate","keywords":"Healthcare; Defense"},{"date":"2024-02-09","bill_number":"SB234","bill_title":"Parking Lot Solar Development Program; established, report.","vote_question":"Senate: Read third time and passed Senate (31-Y 7-N)","vote_result":"Passed (31-7)","member_vote":"Yes","session":"2149","roll_call":"1465126","chamber":"Senate","keywords":"Environment"},{"date":"2024-02-09","bill_number":"SB234","bill_title":"Parking Lot Solar Development Program; established, report.","vote_question":"Senate: Reconsideration of passage agreed to by Senate (37-Y 2-N)","vote_result":"Passed (37-2)","member_vote":"Yes","session":"2149","roll_call":"1465127","chamber":"Senate","keywords":"Environment"},{"date":"2024-02-09","bill_number":"SB234","bill_title":"Parking Lot Solar Development Program; established, report.","vote_question":"Senate: Passed Senate (30-Y 10-N)","vote_result":"Passed (30-10)","member_vote":"Yes","session":"2149","roll_call":"1465128","chamber":"Senate","keywords":"Environment"},{"date":"2024-02-08","bill_number":"SB575","bill_title":"Discharge plans; copies to public elementary and secondary schools.","vote_question":"Senate: Constitutional reading dispensed (40-Y 0-N)","vote_result":"Vote (40-0)","member_vote":"Yes","session":"2149","roll_call":"1464662","chamber":"Senate","keywords":"Healthcare; Education; Criminal Justice; Housing"},{"date":"2024-02-08","bill_number":"SB270","bill_title":"Presidential primaries; ranked choice voting, effective clause.","vote_question":"Senate: Constitutional reading dispensed (40-Y 0-N)","vote_result":"Vote (40-0)","member_vote":"Yes","session":"2149","roll_call":"1464667","chamber":"Senate","keywords":"Elections"},{"date":"2024-02-08","bill_number":"SB636","bill_title":"Transcranial magnetic stimulation; DBHDS to establish pilot program for veterans.","vote_question":"Senate: Constitutional reading dispensed (40-Y 0-N)","vote_result":"Vote (40-0)","member_vote":"Yes","session":"2149","roll_call":"1464705","chamber":"Senate","keywords":"Environment; Defense"},{"date":"2024-02-08","bill_number":"SB359","bill_title":"Consumer Data Protection Act; social media platforms, addictive feed.","vote_question":"Senate: Constitutional reading dispensed (40-Y 0-N)","vote_result":"Vote (40-0)","member_vote":"Yes","session":"2149","roll_call":"1464715","chamber":"Senate","keywords":"Technology; Housing"},{"date":"2024-02-08","bill_number":"SB697","bill_title":"Solar and energy facilities; local regulation.","vote_question":"Senate: Reported from Local Government with substitute (9-Y 6-N)","vote_result":"Vote (9-6)","member_vote":"Yes","session":"2149","roll_call":"1464773","chamber":"Senate","keywords":"Environment"},{"date":"2024-02-08","bill_number":"SB697","bill_title":"Solar and energy facilities; local regulation.","vote_question":"Senate: Constitutional reading dispensed (40-Y 0-N)","vote_result":"Vote (40-0)","member_vote":"Yes","session":"2149","roll_call":"1464774","chamber":"Senate","keywords":"Environment"},{"date":"2024-02-08","bill_number":"SB218","bill_title":"Retirement system; animal control officers to receive benefits.","vote_question":"Senate: Constitutional reading dispensed (40-Y 0-N)","vote_result":"Vote (40-0)","member_vote":"Yes","session":"2149","roll_call":"1464785","chamber":"Senate","keywords":"Healthcare; Housing"},{"date":"2024-02-08","bill_number":"SB218","bill_title":"Retirement system; animal control officers to receive benefits.","vote_question":"Senate: Read third time and passed Senate (40-Y 0-N)","vote_result":"Passed (40-0)","member_vote":"Yes","session":"2149","roll_call":"1464786","chamber":"Senate","keywords":"Healthcare; Housing"},{"date":"2024-02-08","bill_number":"SB593","bill_title":"Workers' compensation benefits; post-traumatic stress disorder incurred by firefighters, etc.","vote_question":"Senate: Constitutional reading dispensed (40-Y 0-N)","vote_result":"Vote (40-0)","member_vote":"Yes","session":"2149","roll_call":"1464854","chamber":"Senate","keywords":""},{"date":"2024-02-08","bill_number":"SB315","bill_title":"Voter registration; registration of DMV customers, updates to existing registration.","vote_question":"Senate: Constitutional reading dispensed (40-Y 0-N)","vote_result":"Vote (40-0)","member_vote":"Yes","session":"2149","roll_call":"1464903","chamber":"Senate","keywords":"Economy; Environment; Housing; Elections"},{"date":"2024-02-08","bill_number":"SB427","bill_title":"Petition for modification of a sentence; eligibility, procedures.","vote_question":"Senate: Constitutional reading dispensed (40-Y 0-N)","vote_result":"Vote (40-0)","member_vote":"Yes","session":"2149","roll_call":"1465009","chamber":"Senate","keywords":"Criminal Justice; Housing"},{"date":"2024-02-08","bill_number":"SB396","bill_title":"Virginia Retirement System; service retirement allowance for certain judges.","vote_question":"Senate: Constitutional reading dispensed (40-Y 0-N)","vote_result":"Vote (40-0)","member_vote":"Yes","session":"2149","roll_call":"1465084","chamber":"Senate","keywords":""},{"date":"2024-02-08","bill_number":"SB396","bill_title":"Virginia Retirement System; service retirement allowance for certain judges.","vote_question":"Senate: Read third time and passed Senate (40-Y 0-N)","vote_result":"Passed (40-0)","member_vote":"Yes","session":"2149","roll_call":"1465085","chamber":"Senate","keywords":""},{"date":"2024-02-07","bill_number":"SB285","bill_title":"Siting of data centers; site assessment.","vote_question":"Senate: Continued to 2025 in General Laws and Technology (13-Y 2-N)","vote_result":"Vote (13-2)","member_vote":"No","session":"2149","roll_call":"1464711","chamber":"Senate","keywords":"Environment; Technology"},{"date":"2024-02-07","bill_number":"SB693","bill_title":"Residential land; prohibited acquisition, restrictions, civil penalty.","vote_question":"Senate: Continued to 2025 in Courts of Justice (15-Y 0-N)","vote_result":"Vote (15-0)","member_vote":"Yes","session":"2149","roll_call":"1464713","chamber":"Senate","keywords":"Economy"},{"date":"2024-02-07","bill_number":"SB359","bill_title":"Consumer Data Protection Act; social media platforms, addictive feed.","vote_question":"Senate: Reported from General Laws and Technology with substitute (14-Y 0-N 1-A)","vote_result":"Vote (14-0)","member_vote":"Yes","session":"2149","roll_call":"1464714","chamber":"Senate","keywords":"Technology; Housing"},{"date":"2024-02-07","bill_number":"SB280","bill_title":"Health care; decision-making, definitions, medical aid in dying, penalties.","vote_question":"Senate: Constitutional reading dispensed (40-Y 0-N)","vote_result":"Vote (40-0)","member_vote":"Yes","session":"2149","roll_call":"1464730","chamber":"Senate","keywords":"Healthcare; Criminal Justice"},{"date":"2024-02-07","bill_number":"SB218","bill_title":"Retirement system; animal control officers to receive benefits.","vote_question":"Senate: Constitutional reading dispensed (40-Y 0-N)","vote_result":"Vote (40-0)","member_vote":"Yes","session":"2149","roll_call":"1464784","chamber":"Senate","keywords":"Healthcare; Housing"},{"date":"2024-02-07","bill_number":"SB519","bill_title":"Divorce; grounds, cruelty, abuse, desertion, or abandonment, eliminates waiting period.","vote_question":"Senate: Continued to 2025 in Courts of Justice (13-Y 2-N)","vote_result":"Vote (13-2)","member_vote":"Yes","session":"2149","roll_call":"1464882","chamber":"Senate","keywords":""},{"date":"2024-02-07","bill_number":"SB284","bill_title":"Siting of data centers; impacts on resources and historically significant sites.","vote_question":"Senate: Continued to 2025 in General Laws and Technology (13-Y 2-N)","vote_result":"Vote (13-2)","member_vote":"No","session":"2149","roll_call":"1464911","chamber":"Senate","keywords":"Technology"},{"date":"2024-02-07","bill_number":"SB647","bill_title":"Virginia Public Procurement Act; apprenticeship programs, competitive sealed bidding.","vote_question":"Senate: Reported from General Laws and Technology with substitute (9-Y 6-N)","vote_result":"Vote (9-6)","member_vote":"Yes","session":"2149","roll_call":"1464984","chamber":"Senate","keywords":"Environment; Infrastructure; Technology; Housing"},{"date":"2024-02-07","bill_number":"SB113","bill_title":"Veterans' Fellowship for State Government Pilot Program; created, report.","vote_question":"Senate: Reported from General Laws and Technology (15-Y 0-N)","vote_result":"Vote (15-0)","member_vote":"Yes","session":"2149","roll_call":"1464987","chamber":"Senate","keywords":"Education; Economy; Environment; Defense; Technology"},{"date":"2024-02-07","bill_number":"SB302","bill_title":"Virginia First Manufacturing Incentive Program; Manufacturing Development Commission to create.","vote_question":"Senate: Reported from General Laws and Technology with substitute (14-Y 0-N)","vote_result":"Vote (14-0)","member_vote":"Yes","session":"2149","roll_call":"1464991","chamber":"Senate","keywords":"Economy; Infrastructure; Technology"},{"date":"2024-02-07","bill_number":"SB164","bill_title":"Virginia Consumer Protection Act; prohibited practices, artificial intelligence disclosure.","vote_question":"Senate: Continued to 2025 in General Laws and Technology (15-Y 0-N)","vote_result":"Vote (15-0)","member_vote":"Yes","session":"2149","roll_call":"1465066","chamber":"Senate","keywords":"Technology"},{"date":"2024-02-07","bill_number":"SB396","bill_title":"Virginia Retirement System; service retirement allowance for certain judges.","vote_question":"Senate: Constitutional reading dispensed (40-Y 0-N)","vote_result":"Vote (40-0)","member_vote":"Yes","session":"2149","roll_call":"1465083","chamber":"Senate","keywords":""},{"date":"2024-02-07","bill_number":"SB234","bill_title":"Parking Lot Solar Development Program; established, report.","vote_question":"Senate: Constitutional reading dispensed (40-Y 0-N)","vote_result":"Vote (40-0)","member_vote":"Yes","session":"2149","roll_call":"1465125","chamber":"Senate","keywords":"Environment"},{"date":"2024-02-07","bill_number":"SB492","bill_title":"Va. Public Procurement Act; procurement of electric vehicles, forced and child labor prohibition.","vote_question":"Senate: Continued to 2025 in General Laws and Technology (9-Y 6-N)","vote_result":"Vote (9-6)","member_vote":"Yes","session":"2149","roll_call":"1465182","chamber":"Senate","keywords":"Economy; Technology"},{"date":"2024-02-07","bill_number":"SB596","bill_title":"Virginia Residential Landlord and Tenant Act; noncompliance with rental agreement.","vote_question":"Senate: Continued to 2025 in General Laws and Technology (15-Y 0-N)","vote_result":"Vote (15-0)","member_vote":"Yes","session":"2149","roll_call":"1465227","chamber":"Senate","keywords":"Technology; Housing"},{"date":"2024-02-06","bill_number":"SB304","bill_title":"Zoning; development and use of accessory dwelling units.","vote_question":"Senate: Constitutional reading dispensed (39-Y 0-N)","vote_result":"Vote (39-0)","member_vote":"Yes","session":"2149","roll_call":"1464895","chamber":"Senate","keywords":""},{"date":"2024-02-06","bill_number":"SB226","bill_title":"Highway use fee; DMV to convene work group to determine tiered flat rate system, report.","vote_question":"Senate: Constitutional reading dispensed (39-Y 0-N)","vote_result":"Vote (39-0)","member_vote":"Yes","session":"2149","roll_call":"1464925","chamber":"Senate","keywords":"Environment; Infrastructure"},{"date":"2024-02-06","bill_number":"SB226","bill_title":"Highway use fee; DMV to convene work group to determine tiered flat rate system, report.","vote_question":"Senate: Passed Senate (39-Y 0-N)","vote_result":"Passed (39-0)","member_vote":"Yes","session":"2149","roll_call":"1464926","chamber":"Senate","keywords":"Environment; Infrastructure"},{"date":"2024-02-06","bill_number":"SB377","bill_title":"Campaign finance; prohibited personal use of campaign funds, complaints, hearings, civil penalty.","vote_question":"Senate: Read third time and passed Senate (35-Y 4-N)","vote_result":"Passed (35-4)","member_vote":"Yes","session":"2149","roll_call":"1464960","chamber":"Senate","keywords":"Housing; Social Services; Elections"},{"date":"2024-02-05","bill_number":"SB305","bill_title":"Gas-powered leaf blowers; local prohibition or regulation, civil penalty.","vote_question":"Senate: Continued to 2025 in Local Government (11-Y 4-N)","vote_result":"Vote (11-4)","member_vote":"No","session":"2149","roll_call":"1464660","chamber":"Senate","keywords":""},{"date":"2024-02-05","bill_number":"SB482","bill_title":"Juveniles; expungement and sealing of court records.","vote_question":"Senate: Continued to 2025 in Courts of Justice (15-Y 0-N)","vote_result":"Vote (15-0)","member_vote":"Yes","session":"2149","roll_call":"1464691","chamber":"Senate","keywords":"Housing"},{"date":"2024-02-05","bill_number":"SB304","bill_title":"Zoning; development and use of accessory dwelling units.","vote_question":"Senate: Reported from Local Government with substitute (8-Y 6-N 1-A)","vote_result":"Vote (8-6)","member_vote":"Yes","session":"2149","roll_call":"1464894","chamber":"Senate","keywords":""},{"date":"2024-02-05","bill_number":"SB226","bill_title":"Highway use fee; DMV to convene work group to determine tiered flat rate system, report.","vote_question":"Senate: Constitutional reading dispensed (39-Y 0-N)","vote_result":"Vote (39-0)","member_vote":"Yes","session":"2149","roll_call":"1464924","chamber":"Senate","keywords":"Environment; Infrastructure"},{"date":"2024-02-05","bill_number":"SB229","bill_title":"Breakthrough Therapies for Veteran Suicide Prevention, Advisory Council on; placement of Council.","vote_question":"Senate: Read third time and passed Senate (35-Y 5-N)","vote_result":"Passed (35-5)","member_vote":"Yes","session":"2149","roll_call":"1464940","chamber":"Senate","keywords":"Healthcare; Defense; Infrastructure"},{"date":"2024-02-05","bill_number":"SB427","bill_title":"Petition for modification of a sentence; eligibility, procedures.","vote_question":"Senate: Reported from Courts of Justice with substitute (9-Y 6-N)","vote_result":"Vote (9-6)","member_vote":"Yes","session":"2149","roll_call":"1465007","chamber":"Senate","keywords":"Criminal Justice; Housing"},{"date":"2024-02-05","bill_number":"SB181","bill_title":"Public elementary and secondary schools; cardiac emergency response plans required.","vote_question":"Senate: Read third time and passed Senate (40-Y 0-N)","vote_result":"Passed (40-0)","member_vote":"Yes","session":"2149","roll_call":"1465198","chamber":"Senate","keywords":"Healthcare; Education; Economy; Environment"},{"date":"2024-02-02","bill_number":"SB390","bill_title":"SUDP; Office of Chief Medical Examiner to publish information on its website.","vote_question":"Senate: Constitutional reading dispensed (38-Y 0-N)","vote_result":"Vote (38-0)","member_vote":"Yes","session":"2149","roll_call":"1464942","chamber":"Senate","keywords":"Healthcare"},{"date":"2024-02-01","bill_number":"SB229","bill_title":"Breakthrough Therapies for Veteran Suicide Prevention, Advisory Council on; placement of Council.","vote_question":"Senate: Constitutional reading dispensed (40-Y 0-N)","vote_result":"Vote (40-0)","member_vote":"Yes","session":"2149","roll_call":"1464939","chamber":"Senate","keywords":"Healthcare; Defense; Infrastructure"},{"date":"2024-02-01","bill_number":"SB377","bill_title":"Campaign finance; prohibited personal use of campaign funds, complaints, hearings, civil penalty.","vote_question":"Senate: Constitutional reading dispensed (40-Y 0-N)","vote_result":"Vote (40-0)","member_vote":"Yes","session":"2149","roll_call":"1464959","chamber":"Senate","keywords":"Housing; Social Services; Elections"},{"date":"2024-02-01","bill_number":"SB181","bill_title":"Public elementary and secondary schools; cardiac emergency response plans required.","vote_question":"Senate: Constitutional reading dispensed (40-Y 0-N)","vote_result":"Vote (40-0)","member_vote":"Yes","session":"2149","roll_call":"1465197","chamber":"Senate","keywords":"Healthcare; Education; Economy; Environment"},{"date":"2024-01-31","bill_number":"SB636","bill_title":"Transcranial magnetic stimulation; DBHDS to establish pilot program for veterans.","vote_question":"Senate: Reported from General Laws and Technology (15-Y 0-N)","vote_result":"Vote (15-0)","member_vote":"Yes","session":"2149","roll_call":"1464703","chamber":"Senate","keywords":"Environment; Defense; Technology"},{"date":"2024-01-31","bill_number":"SB247","bill_title":"Building service employees; public contracting.","vote_question":"Senate: Reported from General Laws and Technology with substitute (8-Y 7-N)","vote_result":"Vote (8-7)","member_vote":"Yes","session":"2149","roll_call":"1464799","chamber":"Senate","keywords":"Education; Environment; Infrastructure; Technology; Agriculture"},{"date":"2024-01-31","bill_number":"SB278","bill_title":"Virginia Abortion Care & Gender-Affirming Health Care Protection Act; established, civil penalties.","vote_question":"Senate: Continued to 2025 in Courts of Justice (15-Y 0-N)","vote_result":"Vote (15-0)","member_vote":"Yes","session":"2149","roll_call":"1464822","chamber":"Senate","keywords":"Healthcare; Criminal Justice"},{"date":"2024-01-31","bill_number":"SB432","bill_title":"Consumer Data Protection Act; protections for children.","vote_question":"Senate: Continued to 2025 in General Laws and Technology (8-Y 7-N)","vote_result":"Vote (8-7)","member_vote":"No","session":"2149","roll_call":"1464917","chamber":"Senate","keywords":"Technology; Housing"},{"date":"2024-01-31","bill_number":"SB684","bill_title":"Online Children's Safety Protection Act; established, civil penalties.","vote_question":"Senate: Continued to 2025 in General Laws and Technology (8-Y 6-N 1-A)","vote_result":"Vote (8-6)","member_vote":"Not Voting","session":"2149","roll_call":"1464982","chamber":"Senate","keywords":"Technology"},{"date":"2024-01-31","bill_number":"SB633","bill_title":"Court fines and fees; indigent defendant, waiver of fees.","vote_question":"Senate: Reported from Courts of Justice with substitute (10-Y 5-N)","vote_result":"Vote (10-5)","member_vote":"Yes","session":"2149","roll_call":"1465019","chamber":"Senate","keywords":"Criminal Justice"},{"date":"2024-01-31","bill_number":"SJR26","bill_title":"Drugs; JLARC to study scope and cost of penalizing possession as a felony.","vote_question":"Senate: Agreed to by Senate (21-Y 19-N)","vote_result":"Passed (21-19)","member_vote":"Yes","session":"2149","roll_call":"1465057","chamber":"Senate","keywords":"Healthcare; Housing"},{"date":"2024-01-31","bill_number":"SJR26","bill_title":"Drugs; JLARC to study scope and cost of penalizing possession as a felony.","vote_question":"Senate: Reconsideration of passage agreed to by Senate (40-Y 0-N)","vote_result":"Passed (40-0)","member_vote":"Yes","session":"2149","roll_call":"1465058","chamber":"Senate","keywords":"Healthcare; Housing"},{"date":"2024-01-31","bill_number":"SJR26","bill_title":"Drugs; JLARC to study scope and cost of penalizing possession as a felony.","vote_question":"Senate: Agreed to by Senate (22-Y 18-N)","vote_result":"Passed (22-18)","member_vote":"Yes","session":"2149","roll_call":"1465059","chamber":"Senate","keywords":"Healthcare; Housing"},{"date":"2024-01-31","bill_number":"SB252","bill_title":"Consumer Data Protection Act; controller privacy notice, consumer consent.","vote_question":"Senate: Continued to 2025 in General Laws and Technology (15-Y 0-N)","vote_result":"Vote (15-0)","member_vote":"Yes","session":"2149","roll_call":"1465157","chamber":"Senate","keywords":"Technology"},{"date":"2024-01-30","bill_number":"SB457","bill_title":"Driving Decarbonization Program and Fund; established and created.","vote_question":"Senate: Reported from Agriculture, Conservation and Natural Resources with substitute (15-Y 0-N)","vote_result":"Vote (15-0)","member_vote":"Yes","session":"2149","roll_call":"1464679","chamber":"Senate","keywords":"Environment; Agriculture"},{"date":"2024-01-30","bill_number":"SB665","bill_title":"Southwest Regional Recreation Authority; soil erosion control and stormwater management plans.","vote_question":"Senate: Continued to 2025 in Agriculture, Conservation and Natural Resources (9-Y 6-N)","vote_result":"Vote (9-6)","member_vote":"Yes","session":"2149","roll_call":"1464727","chamber":"Senate","keywords":"Environment; Agriculture"},{"date":"2024-01-30","bill_number":"SB733","bill_title":"Chief Resilience Officer of the Commonwealth; moves position under the Governor.","vote_question":"Senate: Reported from Agriculture, Conservation and Natural Resources with amendment (15-Y 0-N)","vote_result":"Vote (15-0)","member_vote":"Yes","session":"2149","roll_call":"1464781","chamber":"Senate","keywords":"Environment; Agriculture"},{"date":"2024-01-30","bill_number":"SB33","bill_title":"Certified registered nurse anesthetists; supervision during an operation or procedure.","vote_question":"Senate: Read third time and passed Senate (34-Y 6-N)","vote_result":"Passed (34-6)","member_vote":"Yes","session":"2149","roll_call":"1464876","chamber":"Senate","keywords":"Healthcare; Education; Economy; Environment"},{"date":"2024-01-30","bill_number":"SB730","bill_title":"Nonliving shoreline stabilization structures; regulations.","vote_question":"Senate: Continued to 2025 in Agriculture, Conservation and Natural Resources (15-Y 0-N)","vote_result":"Vote (15-0)","member_vote":"Yes","session":"2149","roll_call":"1465001","chamber":"Senate","keywords":"Environment; Agriculture"},{"date":"2024-01-30","bill_number":"SB698","bill_title":"Dam Safety, Flood Prevention, and Protection Assistance Fund; percentage of funds available.","vote_question":"Senate: Reported from Agriculture, Conservation and Natural Resources (15-Y 0-N)","vote_result":"Vote (15-0)","member_vote":"Yes","session":"2149","roll_call":"1465094","chamber":"Senate","keywords":"Environment; Agriculture"},{"date":"2024-01-30","bill_number":"SB465","bill_title":"Virginia Land Conservation Foundation; land trusts that have been accredited, etc.","vote_question":"Senate: Continued to 2025 in Agriculture, Conservation and Natural Resources (15-Y 0-N)","vote_result":"Vote (15-0)","member_vote":"Yes","session":"2149","roll_call":"1465129","chamber":"Senate","keywords":"Environment; Agriculture; Housing"},{"date":"2024-01-29","bill_number":"SB406","bill_title":"Political campaign advertisements; advertisements sponsored by a person or nonparty committee.","vote_question":"Senate: Read third time and passed Senate (40-Y 0-N)","vote_result":"Passed (40-0)","member_vote":"Yes","session":"2149","roll_call":"1464678","chamber":"Senate","keywords":"Elections"},{"date":"2024-01-29","bill_number":"SB721","bill_title":"Local government actions related to comprehensive plans, etc.; approval process.","vote_question":"Senate: Continued to 2025 in Local Government (15-Y 0-N)","vote_result":"Vote (15-0)","member_vote":"Yes","session":"2149","roll_call":"1464820","chamber":"Senate","keywords":"Housing"},{"date":"2024-01-29","bill_number":"SJR21","bill_title":"Secretariat of Rural Affairs; JLARC to study need for and feasibility of creating position.","vote_question":"Senate: Reading waived (40-Y 0-N)","vote_result":"Vote (40-0)","member_vote":"Yes","session":"2149","roll_call":"1464907","chamber":"Senate","keywords":"Agriculture"},{"date":"2024-01-29","bill_number":"SB371","bill_title":"Planning districts; King George County.","vote_question":"Senate: Continued to 2025 in Local Government (8-Y 7-N)","vote_result":"Vote (8-7)","member_vote":"Yes","session":"2149","roll_call":"1464979","chamber":"Senate","keywords":"Environment; Infrastructure; Housing"},{"date":"2024-01-29","bill_number":"SB612","bill_title":"Local law enforcement; reduction of budget prohibited, exception.","vote_question":"Senate: Continued to 2025 in Local Government (15-Y 0-N)","vote_result":"Vote (15-0)","member_vote":"Yes","session":"2149","roll_call":"1465000","chamber":"Senate","keywords":"Economy"},{"date":"2024-01-29","bill_number":"SJR26","bill_title":"Drugs; JLARC to study scope and cost of penalizing possession as a felony.","vote_question":"Senate: Reading waived (40-Y 0-N)","vote_result":"Passed (40-0)","member_vote":"Yes","session":"2149","roll_call":"1465056","chamber":"Senate","keywords":"Healthcare; Housing"},{"date":"2024-01-29","bill_number":"SB430","bill_title":"Residential development in certain areas; affordable housing.","vote_question":"Senate: Continued to 2025 in Local Government (15-Y 0-N)","vote_result":"Vote (15-0)","member_vote":"Yes","session":"2149","roll_call":"1465146","chamber":"Senate","keywords":"Environment; Agriculture; Housing"},{"date":"2024-01-26","bill_number":"SB33","bill_title":"Certified registered nurse anesthetists; supervision during an operation or procedure.","vote_question":"Senate: Constitutional reading dispensed (37-Y 0-N)","vote_result":"Vote (37-0)","member_vote":"Yes","session":"2149","roll_call":"1464875","chamber":"Senate","keywords":"Healthcare; Education; Economy; Environment"},{"date":"2024-01-26","bill_number":"SB171","bill_title":"Zoning; enhanced civil penalties for violations involving nonpermitted commercial uses.","vote_question":"Senate: Read third time and passed Senate (30-Y 7-N)","vote_result":"Passed (30-7)","member_vote":"Yes","session":"2149","roll_call":"1465204","chamber":"Senate","keywords":""},{"date":"2024-01-25","bill_number":"SB406","bill_title":"Political campaign advertisements; advertisements sponsored by a person or nonparty committee.","vote_question":"Senate: Constitutional reading dispensed (40-Y 0-N)","vote_result":"Vote (40-0)","member_vote":"Yes","session":"2149","roll_call":"1464677","chamber":"Senate","keywords":"Elections"},{"date":"2024-01-24","bill_number":"SB694","bill_title":"Skill games; exceptions.","vote_question":"Senate: Continued to 2025 in General Laws and Technology (15-Y 0-N)","vote_result":"Vote (15-0)","member_vote":"Yes","session":"2149","roll_call":"1464719","chamber":"Senate","keywords":"Technology"},{"date":"2024-01-24","bill_number":"SB124","bill_title":"Sports betting; permitted on Virginia college sports.","vote_question":"Senate: Reported from General Laws and Technology (12-Y 2-N 1-A)","vote_result":"Vote (12-2)","member_vote":"Yes","session":"2149","roll_call":"1465051","chamber":"Senate","keywords":"Education; Technology; Housing"},{"date":"2024-01-24","bill_number":"SB648","bill_title":"Fire and Emergency Medical Services Grant Fund; increases vehicle registration fees.","vote_question":"Senate: Reported from General Laws and Technology with substitute (10-Y 3-N 2-A)","vote_result":"Vote (10-3)","member_vote":"Yes","session":"2149","roll_call":"1465092","chamber":"Senate","keywords":"Healthcare; Technology"},{"date":"2024-01-24","bill_number":"SJR14","bill_title":"Artificial intelligence; Joint Commission on Technology and Science to study advancements.","vote_question":"Senate: Rereferred from General Laws and Technology (15-Y 0-N)","vote_result":"Vote (15-0)","member_vote":"Yes","session":"2149","roll_call":"1465097","chamber":"Senate","keywords":"Economy; Technology; Civil Rights"},{"date":"2024-01-24","bill_number":"SB481","bill_title":"Abolition of juvenile fines and fees; criminal offenses.","vote_question":"Senate: Reported from Courts of Justice with substitute (11-Y 4-N)","vote_result":"Vote (11-4)","member_vote":"Yes","session":"2149","roll_call":"1465168","chamber":"Senate","keywords":"Criminal Justice; Housing"},{"date":"2024-01-24","bill_number":"SB233","bill_title":"Faith in Housing for the Commonwealth Act; construction of affordable housing.","vote_question":"Senate: Continued to 2025 in General Laws and Technology (15-Y 0-N)","vote_result":"Vote (15-0)","member_vote":"Yes","session":"2149","roll_call":"1465170","chamber":"Senate","keywords":"Technology; Housing"},{"date":"2024-01-24","bill_number":"SB689","bill_title":"Casino gaming; cruise ship gaming in the offshore waters of the Commonwealth.","vote_question":"Senate: Reported from General Laws and Technology with substitute (14-Y 1-N)","vote_result":"Vote (14-1)","member_vote":"Yes","session":"2149","roll_call":"1465172","chamber":"Senate","keywords":"Technology"},{"date":"2024-01-24","bill_number":"SB675","bill_title":"Casino gaming; eligible host localities.","vote_question":"Senate: Reported from General Laws and Technology with substitute (10-Y 4-N 1-A)","vote_result":"Vote (10-4)","member_vote":"Yes","session":"2149","roll_call":"1465174","chamber":"Senate","keywords":"Healthcare; Economy; Technology"},{"date":"2024-01-23","bill_number":"SB665","bill_title":"Southwest Regional Recreation Authority; soil erosion control and stormwater management plans.","vote_question":"Senate: Passed by indefinitely in Agriculture, Conservation and Natural Resources (9-Y 6-N)","vote_result":"Passed (9-6)","member_vote":"Yes","session":"2149","roll_call":"1464726","chamber":"Senate","keywords":"Environment; Agriculture"},{"date":"2024-01-23","bill_number":"SB31","bill_title":"Companion Animal Surgical Sterilization Program and Fund; established and created.","vote_question":"Senate: Reported from Agriculture, Conservation and Natural Resources with amendment (9-Y 6-N)","vote_result":"Vote (9-6)","member_vote":"Yes","session":"2149","roll_call":"1464839","chamber":"Senate","keywords":"Economy; Environment; Agriculture"},{"date":"2024-01-23","bill_number":"SB557","bill_title":"Renewable energy portfolio standard; eligibility of hydrogen and nuclear resources.","vote_question":"Senate: Continued to 2025 in Agriculture, Conservation and Natural Resources (13-Y 2-N)","vote_result":"Vote (13-2)","member_vote":"Yes","session":"2149","roll_call":"1464935","chamber":"Senate","keywords":"Environment; Agriculture"},{"date":"2024-01-23","bill_number":"SB289","bill_title":"Stormwater management regulations; enterprise data center operations.","vote_question":"Senate: Continued to 2025 in Agriculture, Conservation and Natural Resources (10-Y 5-N)","vote_result":"Vote (10-5)","member_vote":"No","session":"2149","roll_call":"1464971","chamber":"Senate","keywords":"Environment; Agriculture"},{"date":"2024-01-23","bill_number":"SB446","bill_title":"Environmental Resources, Board of; created.","vote_question":"Senate: Continued to 2025 in Agriculture, Conservation and Natural Resources (15-Y 0-N)","vote_result":"Vote (15-0)","member_vote":"Yes","session":"2149","roll_call":"1465064","chamber":"Senate","keywords":"Environment; Agriculture"},{"date":"2024-01-23","bill_number":"SB171","bill_title":"Zoning; enhanced civil penalties for violations involving nonpermitted commercial uses.","vote_question":"Senate: Constitutional reading dispensed (39-Y 0-N)","vote_result":"Vote (39-0)","member_vote":"Yes","session":"2149","roll_call":"1465203","chamber":"Senate","keywords":""},{"date":"2024-01-23","bill_number":"SB562","bill_title":"Captured coal mine methane; pilot program, renewable energy portfolio standard.","vote_question":"Senate: Continued to 2025 in Agriculture, Conservation and Natural Resources (14-Y 1-N)","vote_result":"Vote (14-1)","member_vote":"Yes","session":"2149","roll_call":"1465217","chamber":"Senate","keywords":"Environment; Agriculture"},{"date":"2024-01-22","bill_number":"SB136","bill_title":"Local government; prohibition on certain appointments.","vote_question":"Senate: Continued to 2025 in Local Government (12-Y 3-N)","vote_result":"Vote (12-3)","member_vote":"Yes","session":"2149","roll_call":"1464968","chamber":"Senate","keywords":"Housing"},{"date":"2024-01-22","bill_number":"SB200","bill_title":"Legal notices; locality to advertise on their website.","vote_question":"Senate: Continued to 2025 in Local Government (13-Y 2-N)","vote_result":"Vote (13-2)","member_vote":"Yes","session":"2149","roll_call":"1465120","chamber":"Senate","keywords":""},{"date":"2024-01-22","bill_number":"SB163","bill_title":"Southwest Regional Recreation Authority; powers.","vote_question":"Senate: Reported from Local Government (15-Y 0-N)","vote_result":"Vote (15-0)","member_vote":"Yes","session":"2149","roll_call":"1465158","chamber":"Senate","keywords":"Environment"},{"date":"2024-01-22","bill_number":"SB171","bill_title":"Zoning; enhanced civil penalties for violations involving nonpermitted commercial uses.","vote_question":"Senate: Reported from Local Government with amendments (9-Y 4-N 2-A)","vote_result":"Vote (9-4)","member_vote":"Yes","session":"2149","roll_call":"1465202","chamber":"Senate","keywords":""},{"date":"2024-01-18","bill_number":"SB332","bill_title":"Misdemeanor; maximum term of confinement.","vote_question":"Senate: Read third time and passed Senate (21-Y 19-N)","vote_result":"Passed (21-19)","member_vote":"Yes","session":"2149","roll_call":"1464976","chamber":"Senate","keywords":"Environment; Criminal Justice"},{"date":"2024-01-17","bill_number":"SB322","bill_title":"Primary evacuation routes; statewide prioritization process.","vote_question":"Senate: Rereferred from General Laws and Technology (15-Y 0-N)","vote_result":"Vote (15-0)","member_vote":"Yes","session":"2149","roll_call":"1465180","chamber":"Senate","keywords":"Infrastructure; Technology; Elections"},{"date":"2024-01-16","bill_number":"SJR1","bill_title":"Constitutional amendment; fundamental right to reproductive freedom (first reference).","vote_question":"Senate: Continued to 2025 in Privileges and Elections (14-Y 0-N)","vote_result":"Vote (14-0)","member_vote":"Yes","session":"2149","roll_call":"1464692","chamber":"Senate","keywords":"Healthcare; Elections"},{"date":"2024-01-16","bill_number":"SB332","bill_title":"Misdemeanor; maximum term of confinement.","vote_question":"Senate: Constitutional reading dispensed (38-Y 0-N)","vote_result":"Vote (38-0)","member_vote":"Yes","session":"2149","roll_call":"1464975","chamber":"Senate","keywords":"Environment; Criminal Justice"},{"date":"2024-01-16","bill_number":"SJR10","bill_title":"Constitutional amendment; term limits for Lieutenant Governor & Attorney General (first reference).","vote_question":"Senate: Continued to 2025 in Privileges and Elections (14-Y 0-N)","vote_result":"Vote (14-0)","member_vote":"Yes","session":"2149","roll_call":"1465190","chamber":"Senate","keywords":"Elections"},{"date":"2024-01-16","bill_number":"SJR2","bill_title":"Constitutional amendment; qualifications of voters, right to vote, persons not entitled to vote.","vote_question":"Senate: Continued to 2025 in Privileges and Elections (14-Y 0-N)","vote_result":"Vote (14-0)","member_vote":"Yes","session":"2149","roll_call":"1465201","chamber":"Senate","keywords":"Economy; Infrastructure; Housing; Civil Rights; Elections"},{"date":"2024-01-16","bill_number":"SJR11","bill_title":"Constitutional amendment; marriage between two individuals.","vote_question":"Senate: Continued to 2025 in Privileges and Elections (14-Y 0-N)","vote_result":"Vote (14-0)","member_vote":"Yes","session":"2149","roll_call":"1465218","chamber":"Senate","keywords":"Housing; Elections"},{"date":"2024-01-15","bill_number":"SB332","bill_title":"Misdemeanor; maximum term of confinement.","vote_question":"Senate: Reported from Courts of Justice (8-Y 7-N)","vote_result":"Vote (8-7)","member_vote":"Yes","session":"2149","roll_call":"1464974","chamber":"Senate","keywords":"Environment; Criminal Justice"},{"date":"2024-01-15","bill_number":"SB123","bill_title":"Improvements, repairs, or maintenance of property; entering adjoining property, petition for entry.","vote_question":"Senate: Continued to 2025 in Courts of Justice (15-Y 0-N)","vote_result":"Vote (15-0)","member_vote":"Yes","session":"2149","roll_call":"1465023","chamber":"Senate","keywords":"Economy; Environment"},{"date":"2024-01-15","bill_number":"SB197","bill_title":"Attorney General; instituting or conducting criminal prosecutions.","vote_question":"Senate: Reported from Courts of Justice with amendments (9-Y 6-N)","vote_result":"Vote (9-6)","member_vote":"No","session":"2149","roll_call":"1465166","chamber":"Senate","keywords":"Criminal Justice"}]